auth/__init__.py
auth/common.py
auth/flask.py
tests/__init__.py
tests/test_auth.py
ky_auth_utils-0.1.0.dist-info/METADATA
ky_auth_utils-0.1.0.dist-info/WHEEL
ky_auth_utils-0.1.0.dist-info/top_level.txt
ky_auth_utils-0.1.0.dist-info/RECORD
